[
  {
    "id": "U012C71MHE0",
    "mail": "lazaro.ansaldi@southworks.com"
  },
  {
    "id": "UL8NHUS8Z",
    "mail": "joaquin.fiora@southworks.com"
  },
  {
    "id": "U0103909GC8",
    "mail": "mirco.fiocchi@southworks.com"
  },
  {
    "id": "UEJ1TE6HJ",
    "mail": "eloy.vega@southworks.com"
  },
  {
    "id": "U8TQW1DPG",
    "mail": "christian.gelman@southworks.com"
  },
  {
    "id": "U014T5HCN3E",
    "mail": "alejo.pereyra@southworks.com"
  },
  {
    "id": "U015MN7QZV4",
    "mail": "i-nmachulsky@southworks.com"
  },
  {
    "id": "UMLP2663D",
    "mail": "damian.steimberg@southworks.com"
  },
  {
    "id": "U013TKBHSKX",
    "mail": "nadia.chiappero@southworks.com"
  },
  {
    "id": "UE1KF7C1H",
    "mail": "santiago.gomez@southworks.com"
  },
  {
    "id": "U014M6Z5WM9",
    "mail": "franco.zuccarelli@southworks.com"
  },
  {
    "id": "U014JS2NVNC",
    "mail": "hector.mazzucotelli@southworks.com"
  }
]